{
  "_class": "bitmap",
  "booleanOperation": 0,
  "clippingMask": "{{0, 0}, {1, 1}}",
  "do_objectID": "193D0800-59E8-4AAF-A98E-6BAA4C0388D1",
  "exportOptions": {
    "_class": "exportOptions",
    "exportFormats": [
    ],
    "includedLayerIds": [
    ],
    "layerOptions": 0,
    "shouldTrim": false
  },
  "fillReplacesImage": false,
  "frame": {
    "_class": "rect",
    "constrainProportions": true,
    "height": 104,
    "width": 156,
    "x": -22,
    "y": -30
  },
  "image": {
    "_class": "MSJSONFileReference",
    "_ref": "images/11fd42bdca51c2ece8385332b340cb179c0e41b4.png",
    "_ref_class": "MSImageData"
  },
  "intendedDPI": 0,
  "isFixedToViewport": false,
  "isFlippedHorizontal": false,
  "isFlippedVertical": false,
  "isLocked": false,
  "isVisible": true,
  "layerListExpandedType": 0,
  "name": "image",
  "nameIsFixed": true,
  "resizingConstraint": 63,
  "resizingType": 0,
  "rotation": 0,
  "shouldBreakMaskChain": false,
  "style": {
    "_class": "style",
    "endMarkerType": 0,
    "fills": [
      {
        "_class": "fill",
        "color": {
          "_class": "color",
          "alpha": 1,
          "blue": 0.847,
          "green": 0.847,
          "red": 0.847
        },
        "fillType": 4,
        "image": {
          "_class": "MSJSONFileReference",
          "_ref": "images/5c9f36f91d691b7c693795152776640c2c309539.png",
          "_ref_class": "MSImageData"
        },
        "isEnabled": true,
        "noiseIndex": 0,
        "noiseIntensity": 0,
        "patternFillType": 1,
        "patternTileScale": 1
      }
    ],
    "miterLimit": 10,
    "startMarkerType": 0,
    "windingRule": 1
  },
  "userInfo": {
    "com.animaapp.stc-sketch-plugin": {
      "kModelPropertiesKey": {
        "constraints": {
          "aspectRatio": {
            "constant": 104,
            "enabled": 1,
            "modelID": "constraint_ee6f4f5c-f09b-4e25-87e3-fe5104df050f",
            "model_class": "ADModelConstraint",
            "model_version": 0.1,
            "multiplier": 155.7219
          },
          "automatic": 1,
          "modelID": "viewConstraints_abb032a9-85c7-4898-a592-b35a9aa7c727",
          "model_class": "ADModelViewConstraints",
          "model_version": 0.1
        }
      }
    }
  }
}